agents/__init__.py
agents/server.py
functions/__init__.py
functions/server.py
monitoring_server/__init__.py
monitoring_server/main.py
monitoring_server/settings.py
monitoring_server/agents/__init__.py
monitoring_server/agents/server.py
monitoring_server/functions/__init__.py
monitoring_server/functions/server.py
monitoring_server-0.1.3.dist-info/METADATA
monitoring_server-0.1.3.dist-info/WHEEL
monitoring_server-0.1.3.dist-info/entry_points.txt
monitoring_server-0.1.3.dist-info/top_level.txt
monitoring_server-0.1.3.dist-info/RECORD
