Metadata-Version: 2.1
Name: monitoring-server
Version: 0.1.3
Summary: Monitorear recursos (ram, procesador y disco) de un server
Home-page: https://github.com/arielespinosa/CloudWFS-ServerMonitoring
Author: Ariel
Author-email: arielpespinosa@gmail.com
License: UNKNOWN
Platform: UNKNOWN
Classifier: Programming Language :: Python :: 3
Classifier: License :: OSI Approved :: MIT License
Classifier: Operating System :: OS Independent
Requires-Python: >=3.8
Requires-Dist: brokers-agents==0.1
Requires-Dist: certifi==2024.8.30
Requires-Dist: charset-normalizer==3.3.2
Requires-Dist: idna==3.10
Requires-Dist: invoke==2.2.0
Requires-Dist: pika==1.3.2
Requires-Dist: psutil==6.0.0
Requires-Dist: requests==2.32.3
Requires-Dist: urllib3==2.2.3
